Workbook

Sheet Assumptions
A1: LENDING ASSUMPTIONS
A2: Prime Rate (p.a.) | B2: 0.1175
A3: Bank Margin (p.a.) | B3: 0.02
A4: Effective Annual Rate | B4: 0.1375
A5: Monthly Interest Rate | B5: =B4/12 -> 0.011458333
A7: POLICY THRESHOLDS
A8: Max DTI (Approve) | B8: 0.35
A9: Max DTI (Review) | B9: 0.5
A10: Min Surplus (Approve, ZAR) | B10: 8000
A11: Min Surplus (Review, ZAR) | B11: 3000
A12: Min Credit Score (Approve) | B12: 650
A13: Min Credit Score (Review) | B13: 580
A15: SCORE THRESHOLDS
A16: Approve Threshold (≥) | B16: 68
A17: Review Threshold (≥) | B17: 42
A18: Max Possible Score | B18: 100

Sheet Inputs
A1: SA RETAIL CREDIT SCORECARD | APPLICANT INPUT DATA | FY2025
A2: APPLICANT PROFILE (hardcoded inputs — blue) | L2: DERIVED RATIOS (formula outputs — black)
A3: Applicant ID | B3: Age | C3: Province | D3: Employment Status | E3: Gross Monthly Income (R) | F3: Monthly Living Expenses (R) | G3: Existing Debt Repayments (R) | H3: Loan Amount Requested (R) | I3: Loan Term (Months) | J3: Credit Score | K3: Missed Pymnts (12 Mths) | L3: Years in Current Role | M3: Net Disposable Income (R) | N3: Est. Monthly Instalment (R) | O3: Debt-to-Income Ratio | P3: Affordability Surplus (R)
A4: SA-2025-001 | B4: 34 | C4: Gauteng | D4: Permanently Employed | E4: 52000 | F4: 19500 | G4: 5500 | H4: 180000 | I4: 60 | J4: 724 | K4: 0 | L4: 8 | M4: =E4-F4 -> 32500 | N4: =IFERROR(PMT(Assumptions!$B$5,I4,-H4),0) -> 4164.9921 | O4: =IFERROR((G4+N4)/E4,0) -> 0.18586523 | P4: =M4-G4-N4 -> 22835.008
A5: SA-2025-002 | B5: 27 | C5: Western Cape | D5: Permanently Employed | E5: 31000 | F5: 13000 | G5: 3200 | H5: 90000 | I5: 48 | J5: 648 | K5: 1 | L5: 3 | M5: =E5-F5 -> 18000 | N5: =IFERROR(PMT(Assumptions!$B$5,I5,-H5),0) -> 2448.1111 | O5: =IFERROR((G5+N5)/E5,0) -> 0.18219713 | P5: =M5-G5-N5 -> 12351.889
A6: SA-2025-003 | B6: 46 | C6: Gauteng | D6: Self-Employed | E6: 68000 | F6: 27000 | G6: 9000 | H6: 280000 | I6: 72 | J6: 688 | K6: 0 | L6: 14 | M6: =E6-F6 -> 41000 | N6: =IFERROR(PMT(Assumptions!$B$5,I6,-H6),0) -> 5732.1912 | O6: =IFERROR((G6+N6)/E6,0) -> 0.21664987 | P6: =M6-G6-N6 -> 26267.809
A7: SA-2025-004 | B7: 23 | C7: KwaZulu-Natal | D7: Fixed-Term Contract | E7: 19200 | F7: 9500 | G7: 1500 | H7: 48000 | I7: 36 | J7: 594 | K7: 2 | L7: 1 | M7: =E7-F7 -> 9700 | N7: =IFERROR(PMT(Assumptions!$B$5,I7,-H7),0) -> 1634.704 | O7: =IFERROR((G7+N7)/E7,0) -> 0.16326583 | P7: =M7-G7-N7 -> 6565.296
A8: SA-2025-005 | B8: 39 | C8: Gauteng | D8: Permanently Employed | E8: 58000 | F8: 21000 | G8: 28000 | H8: 220000 | I8: 60 | J8: 741 | K8: 0 | L8: 11 | M8: =E8-F8 -> 37000 | N8: =IFERROR(PMT(Assumptions!$B$5,I8,-H8),0) -> 5090.5459 | O8: =IFERROR((G8+N8)/E8,0) -> 0.57052665 | P8: =M8-G8-N8 -> 3909.4541
A9: SA-2025-006 | B9: 31 | C9: Western Cape | D9: Permanently Employed | E9: 36000 | F9: 16000 | G9: 4200 | H9: 110000 | I9: 48 | J9: 672 | K9: 1 | L9: 5 | M9: =E9-F9 -> 20000 | N9: =IFERROR(PMT(Assumptions!$B$5,I9,-H9),0) -> 2992.1358 | O9: =IFERROR((G9+N9)/E9,0) -> 0.19978155 | P9: =M9-G9-N9 -> 12807.864
A10: SA-2025-007 | B10: 29 | C10: Eastern Cape | D10: Unemployed | E10: 0 | F10: 5500 | G10: 0 | H10: 28000 | I10: 24 | J10: 538 | K10: 4 | L10: 0 | M10: =E10-F10 -> -5500 | N10: =IFERROR(PMT(Assumptions!$B$5,I10,-H10),0) -> 1341.0562 | O10: =IFERROR((G10+N10)/E10,0) -> 0 | P10: =M10-G10-N10 -> -6841.0562
A11: SA-2025-008 | B11: 43 | C11: Gauteng | D11: Self-Employed | E11: 82000 | F11: 32000 | G11: 33000 | H11: 320000 | I11: 84 | J11: 714 | K11: 0 | L11: 16 | M11: =E11-F11 -> 50000 | N11: =IFERROR(PMT(Assumptions!$B$5,I11,-H11),0) -> 5952.6974 | O11: =IFERROR((G11+N11)/E11,0) -> 0.4750329 | P11: =M11-G11-N11 -> 11047.303
A12: SA-2025-009 | B12: 36 | C12: Gauteng | D12: Permanently Employed | E12: 44000 | F12: 20000 | G12: 6500 | H12: 130000 | I12: 60 | J12: 697 | K12: 0 | L12: 9 | M12: =E12-F12 -> 24000 | N12: =IFERROR(PMT(Assumptions!$B$5,I12,-H12),0) -> 3008.0498 | O12: =IFERROR((G12+N12)/E12,0) -> 0.21609204 | P12: =M12-G12-N12 -> 14491.95
A13: SA-2025-010 | B13: 26 | C13: Limpopo | D13: Fixed-Term Contract | E13: 23000 | F13: 11500 | G13: 6000 | H13: 62000 | I13: 36 | J13: 618 | K13: 1 | L13: 2 | M13: =E13-F13 -> 11500 | N13: =IFERROR(PMT(Assumptions!$B$5,I13,-H13),0) -> 2111.4926 | O13: =IFERROR((G13+N13)/E13,0) -> 0.35267359 | P13: =M13-G13-N13 -> 3388.5074
A14: SA-2025-011 | B14: 51 | C14: Western Cape | D14: Permanently Employed | E14: 96000 | F14: 37000 | G14: 16000 | H14: 420000 | I14: 84 | J14: 762 | K14: 0 | L14: 23 | M14: =E14-F14 -> 59000 | N14: =IFERROR(PMT(Assumptions!$B$5,I14,-H14),0) -> 7812.9154 | O14: =IFERROR((G14+N14)/E14,0) -> 0.2480512 | P14: =M14-G14-N14 -> 35187.085
A15: SA-2025-012 | B15: 33 | C15: Gauteng | D15: Permanently Employed | E15: 38000 | F15: 17500 | G15: 5800 | H15: 115000 | I15: 60 | J15: 641 | K15: 2 | L15: 5 | M15: =E15-F15 -> 20500 | N15: =IFERROR(PMT(Assumptions!$B$5,I15,-H15),0) -> 2660.9672 | O15: =IFERROR((G15+N15)/E15,0) -> 0.22265703 | P15: =M15-G15-N15 -> 12039.033
... A33: SA-2025-030 | B33: 22 | C33: KwaZulu-Natal | D33: Fixed-Term Contract | E33: 15000 | F33: 7500 | G33: 0 | H33: 32000 | I33: 24 | J33: 548 | K33: 2 | L33: 0 | M33: =E33-F33 -> 7500 | N33: =IFERROR(PMT(Assumptions!$B$5,I33,-H33),0) -> 1532.6357 | O33: =IFERROR((G33+N33)/E33,0) -> 0.10217571 | P33: =M33-G33-N33 -> 5967.3643
A36: COLOUR CODE: Blue = Hardcoded Input | Black = Calculated Formula | Green = Cross-Sheet Link
A37: Interest rate: Prime (11.75%) + Margin (2.00%) = 13.75% p.a. → Monthly rate used in PMT. Source: SARB MPC, Nov 2024.

Sheet Scorecard Logic
A1: SA RETAIL CREDIT SCORECARD | SCORING FRAMEWORK & POINT ALLOCATION | MAX SCORE = 100
A2: SECTION A — SCORING BAND REFERENCE TABLES (used by scoring formulas below)
A4: 1. CREDIT SCORE (ITC Bureau) [max 25 pts] | F4: 2. DEBT-TO-INCOME RATIO (DTI) [max 20 pts] | K4: 3. AFFORDABILITY SURPLUS [max 20 pts]
A5: Condition | B5: Pts | C5: Risk Label | D5: Business Rationale | F5: Condition | G5: Pts | H5: Risk Label | I5: Business Rationale | K5: Condition | L5: Pts | M5: Risk Label | N5: Business Rationale
A6: 750 and above | B6: 25 | C6: Excellent | D6: Prime borrower — minimal default risk per ITC/TransUnion data | F6: Below 30% | G6: 20 | H6: Conservative | I6: Strong repayment capacity; well within NCA 35% guideline | K6: Above R12 000 | L6: 20 | M6: Strong | N6: Substantial buffer — comfortable with new repayment
A7: 700 – 749 | B7: 20 | C7: Good | D7: Low-risk profile; within standard NCA affordability comfort | F7: 30% – 39% | G7: 14 | H7: Manageable | I7: Acceptable; within standard bank DTI policy limits | K7: R6 000 – R12 000 | L7: 14 | M7: Adequate | N7: Acceptable buffer; standard approval range
A8: 650 – 699 | B8: 13 | C8: Fair | D8: Acceptable; borderline affordability — monitor DTI closely | F8: 40% – 49% | G8: 7 | H8: Elevated | I8: Approaching over-indebtedness; manual review warranted | K8: R2 000 – R5 999 | L8: 7 | M8: Marginal | N8: Thin surplus; small income shock creates default risk
A9: 580 – 649 | B9: 5 | C9: Weak | D9: Sub-prime territory; elevated probability of default | F9: 50% – 59% | G9: 2 | H9: High | I9: Over-indebted threshold; NCA S79 referral likely | K9: R0 – R1 999 | L9: 2 | M9: Minimal | N9: Negligible buffer; high sensitivity to rate increases
A10: Below 580 | B10: 0 | C10: Poor | D10: High default risk; NCA section 81 affordability concern | F10: 60% and above | G10: 0 | H10: Critical | I10: Clearly over-indebted per NCR definition; decline recommended | K10: Negative | L10: 0 | M10: Deficit | N10: Cannot service loan — decline on affordability grounds
A11: Note: SA bureau scores (TransUnion/Experian) range 330–850. Threshold of 580 reflects typical bank minimum; 650 is preferred floor for unsecured lending. | F11: Note: DTI = (Existing Debt + New Instalment) / Gross Monthly Income. NCR/NCA guideline suggests max 35–40% for responsible lending. | K11: Note: Surplus = Net Disposable Income − Existing Debt − New Instalment. NCR requires lenders to verify that surplus remains positive post-lending.
A17: 4. EMPLOYMENT STATUS [max 15 pts] | F17: 5. MISSED PAYMENTS (12 Months) [max 10 pts] | K17: 6. TENURE IN CURRENT ROLE [max 10 pts]
A18: Condition | B18: Pts | C18: Risk Label | D18: Business Rationale | F18: Condition | G18: Pts | H18: Risk Label | I18: Business Rationale | K18: Condition | L18: Pts | M18: Risk Label | N18: Business Rationale
A19: Permanently Employed | B19: 15 | C19: Stable | D19: Predictable income; lowest income volatility risk | F19: 0 missed payments | G19: 10 | H19: Clean | I19: No adverse payment behaviour — strongest signal | K19: 10 years or more | L19: 10 | M19: Very Stable | N19: Established career — income sustainability high
A20: Self-Employed | B20: 10 | C20: Variable | D20: Business income subject to volatility; require 2-yr financials | F20: 1 missed payment | G20: 6 | H20: Minor | I20: Isolated incident; investigate cause before deciding | K20: 5 – 9 years | L20: 7 | M20: Stable | N20: Reasonable track record; satisfactory for lending
A21: Fixed-Term Contract | B21: 5 | C21: Moderate | D21: Employed but income continuity uncertain beyond contract end | F21: 2 missed payments | G21: 2 | H21: Concerning | I21: Pattern of default risk; consistent with NCA S86 profile | K21: 2 – 4 years | L21: 4 | M21: Developing | N21: Growing career; acceptable with strong other factors
A22: Unemployed | B22: 0 | C22: High Risk | D22: No verifiable income; decline per NCA affordability rules | F22: 3 or more missed | G22: 0 | H22: Adverse | I22: Chronic arrears; decline recommended regardless of score | K22: Under 2 years | L22: 1 | M22: Early Stage | N22: Income continuity unproven; residual employment risk
A23: Note: Employment type is a primary driver of income certainty. SA banks typically require 3 months payslips for employees; 2 years financials for self-employed. | F23: Note: Sourced from bureau payment profile. 3+ missed payments in 12 months is a standard bank hard-decline trigger. | K23: Note: Job tenure proxies income continuity risk. Combined with employment status it captures the stability dimension that payslips alone do not fully reveal.
A30: SECTION B — APPLICANT SCORE AGGREGATION
A31: Applicant ID | B31: CS Score (/25) | C31: DTI Score (/20) | D31: Surplus Score (/20) | E31: Empl Score (/15) | F31: Missed Pymnt Score (/10) | G31: Tenure Score (/10) | H31: TOTAL SCORE (/100) | I31: Risk Band | J31: Policy Check | K31: Final Decision
A32: =Inputs!A4 -> SA-2025-001 | B32: =IF(Inputs!J4>=750,25,IF(Inputs!J4>=700,20,IF(Inputs!J4>=650,13,IF(Inputs!J4>=580,5,0)))) -> 20 | C32: =IF(Inputs!O4<0.3,20,IF(Inputs!O4<0.4,14,IF(Inputs!O4<0.5,7,IF(Inputs!O4<0.6,2,0)))) -> 20 | D32: =IF(Inputs!P4>12000,20,IF(Inputs!P4>=6000,14,IF(Inputs!P4>=2000,7,IF(Inputs!P4>=0,2,0)))) -> 20 | E32: =IF(Inputs!D4="Permanently Employed",15,IF(Inputs!D4="Self-Employed",10,IF(Inputs!D4="Fixed-Term Contract",5,0))) -> 15 | F32: =IF(Inputs!K4=0,10,IF(Inputs!K4=1,6,IF(Inputs!K4=2,2,0))) -> 10 | G32: =IF(Inputs!L4>=10,10,IF(Inputs!L4>=5,7,IF(Inputs!L4>=2,4,1))) -> 7 | H32: =SUM(B32:G32) -> 92 | I32: =IF(H32>=Assumptions!$B$16,"Low Risk",IF(H32>=Assumptions!$B$17,"Medium Risk","High Risk")) -> Low Risk | J32: =IF(OR(Inputs!K4>=3,Inputs!D4="Unemployed",Inputs!P4<0),"POLICY DECLINE","Pass") -> Pass | K32: =IF(J32="POLICY DECLINE","Decline",IF(H32>=Assumptions!$B$17,"Approve",IF(H32>=Assumptions!$B$18,"Review","Decline"))) -> Approve
A33: =Inputs!A5 -> SA-2025-002 | B33: =IF(Inputs!J5>=750,25,IF(Inputs!J5>=700,20,IF(Inputs!J5>=650,13,IF(Inputs!J5>=580,5,0)))) -> 5 | C33: =IF(Inputs!O5<0.3,20,IF(Inputs!O5<0.4,14,IF(Inputs!O5<0.5,7,IF(Inputs!O5<0.6,2,0)))) -> 20 | D33: =IF(Inputs!P5>12000,20,IF(Inputs!P5>=6000,14,IF(Inputs!P5>=2000,7,IF(Inputs!P5>=0,2,0)))) -> 20 | E33: =IF(Inputs!D5="Permanently Employed",15,IF(Inputs!D5="Self-Employed",10,IF(Inputs!D5="Fixed-Term Contract",5,0))) -> 15 | F33: =IF(Inputs!K5=0,10,IF(Inputs!K5=1,6,IF(Inputs!K5=2,2,0))) -> 6 | G33: =IF(Inputs!L5>=10,10,IF(Inputs!L5>=5,7,IF(Inputs!L5>=2,4,1))) -> 4 | H33: =SUM(B33:G33) -> 70 | I33: =IF(H33>=Assumptions!$B$16,"Low Risk",IF(H33>=Assumptions!$B$17,"Medium Risk","High Risk")) -> Low Risk | J33: =IF(OR(Inputs!K5>=3,Inputs!D5="Unemployed",Inputs!P5<0),"POLICY DECLINE","Pass") -> Pass | K33: =IF(J33="POLICY DECLINE","Decline",IF(H33>=Assumptions!$B$17,"Approve",IF(H33>=Assumptions!$B$18,"Review","Decline"))) -> Approve
A34: =Inputs!A6 -> SA-2025-003 | B34: =IF(Inputs!J6>=750,25,IF(Inputs!J6>=700,20,IF(Inputs!J6>=650,13,IF(Inputs!J6>=580,5,0)))) -> 13 | C34: =IF(Inputs!O6<0.3,20,IF(Inputs!O6<0.4,14,IF(Inputs!O6<0.5,7,IF(Inputs!O6<0.6,2,0)))) -> 20 | D34: =IF(Inputs!P6>12000,20,IF(Inputs!P6>=6000,14,IF(Inputs!P6>=2000,7,IF(Inputs!P6>=0,2,0)))) -> 20 | E34: =IF(Inputs!D6="Permanently Employed",15,IF(Inputs!D6="Self-Employed",10,IF(Inputs!D6="Fixed-Term Contract",5,0))) -> 10 | F34: =IF(Inputs!K6=0,10,IF(Inputs!K6=1,6,IF(Inputs!K6=2,2,0))) -> 10 | G34: =IF(Inputs!L6>=10,10,IF(Inputs!L6>=5,7,IF(Inputs!L6>=2,4,1))) -> 10 | H34: =SUM(B34:G34) -> 83 | I34: =IF(H34>=Assumptions!$B$16,"Low Risk",IF(H34>=Assumptions!$B$17,"Medium Risk","High Risk")) -> Low Risk | J34: =IF(OR(Inputs!K6>=3,Inputs!D6="Unemployed",Inputs!P6<0),"POLICY DECLINE","Pass") -> Pass | K34: =IF(J34="POLICY DECLINE","Decline",IF(H34>=Assumptions!$B$17,"Approve",IF(H34>=Assumptions!$B$18,"Review","Decline"))) -> Approve
A35: =Inputs!A7 -> SA-2025-004 | B35: =IF(Inputs!J7>=750,25,IF(Inputs!J7>=700,20,IF(Inputs!J7>=650,13,IF(Inputs!J7>=580,5,0)))) -> 5 | C35: =IF(Inputs!O7<0.3,20,IF(Inputs!O7<0.4,14,IF(Inputs!O7<0.5,7,IF(Inputs!O7<0.6,2,0)))) -> 20 | D35: =IF(Inputs!P7>12000,20,IF(Inputs!P7>=6000,14,IF(Inputs!P7>=2000,7,IF(Inputs!P7>=0,2,0)))) -> 14 | E35: =IF(Inputs!D7="Permanently Employed",15,IF(Inputs!D7="Self-Employed",10,IF(Inputs!D7="Fixed-Term Contract",5,0))) -> 5 | F35: =IF(Inputs!K7=0,10,IF(Inputs!K7=1,6,IF(Inputs!K7=2,2,0))) -> 2 | G35: =IF(Inputs!L7>=10,10,IF(Inputs!L7>=5,7,IF(Inputs!L7>=2,4,1))) -> 1 | H35: =SUM(B35:G35) -> 47 | I35: =IF(H35>=Assumptions!$B$16,"Low Risk",IF(H35>=Assumptions!$B$17,"Medium Risk","High Risk")) -> Medium Risk | J35: =IF(OR(Inputs!K7>=3,Inputs!D7="Unemployed",Inputs!P7<0),"POLICY DECLINE","Pass") -> Pass | K35: =IF(J35="POLICY DECLINE","Decline",IF(H35>=Assumptions!$B$17,"Approve",IF(H35>=Assumptions!$B$18,"Review","Decline"))) -> Approve
A36: =Inputs!A8 -> SA-2025-005 | B36: =IF(Inputs!J8>=750,25,IF(Inputs!J8>=700,20,IF(Inputs!J8>=650,13,IF(Inputs!J8>=580,5,0)))) -> 20 | C36: =IF(Inputs!O8<0.3,20,IF(Inputs!O8<0.4,14,IF(Inputs!O8<0.5,7,IF(Inputs!O8<0.6,2,0)))) -> 2 | D36: =IF(Inputs!P8>12000,20,IF(Inputs!P8>=6000,14,IF(Inputs!P8>=2000,7,IF(Inputs!P8>=0,2,0)))) -> 7 | E36: =IF(Inputs!D8="Permanently Employed",15,IF(Inputs!D8="Self-Employed",10,IF(Inputs!D8="Fixed-Term Contract",5,0))) -> 15 | F36: =IF(Inputs!K8=0,10,IF(Inputs!K8=1,6,IF(Inputs!K8=2,2,0))) -> 10 | G36: =IF(Inputs!L8>=10,10,IF(Inputs!L8>=5,7,IF(Inputs!L8>=2,4,1))) -> 10 | H36: =SUM(B36:G36) -> 64 | I36: =IF(H36>=Assumptions!$B$16,"Low Risk",IF(H36>=Assumptions!$B$17,"Medium Risk","High Risk")) -> Medium Risk | J36: =IF(OR(Inputs!K8>=3,Inputs!D8="Unemployed",Inputs!P8<0),"POLICY DECLINE","Pass") -> Pass | K36: =IF(J36="POLICY DECLINE","Decline",IF(H36>=Assumptions!$B$17,"Approve",IF(H36>=Assumptions!$B$18,"Review","Decline"))) -> Approve
A37: =Inputs!A9 -> SA-2025-006 | B37: =IF(Inputs!J9>=750,25,IF(Inputs!J9>=700,20,IF(Inputs!J9>=650,13,IF(Inputs!J9>=580,5,0)))) -> 13 | C37: =IF(Inputs!O9<0.3,20,IF(Inputs!O9<0.4,14,IF(Inputs!O9<0.5,7,IF(Inputs!O9<0.6,2,0)))) -> 20 | D37: =IF(Inputs!P9>12000,20,IF(Inputs!P9>=6000,14,IF(Inputs!P9>=2000,7,IF(Inputs!P9>=0,2,0)))) -> 20 | E37: =IF(Inputs!D9="Permanently Employed",15,IF(Inputs!D9="Self-Employed",10,IF(Inputs!D9="Fixed-Term Contract",5,0))) -> 15 | F37: =IF(Inputs!K9=0,10,IF(Inputs!K9=1,6,IF(Inputs!K9=2,2,0))) -> 6 | G37: =IF(Inputs!L9>=10,10,IF(Inputs!L9>=5,7,IF(Inputs!L9>=2,4,1))) -> 7 | H37: =SUM(B37:G37) -> 81 | I37: =IF(H37>=Assumptions!$B$16,"Low Risk",IF(H37>=Assumptions!$B$17,"Medium Risk","High Risk")) -> Low Risk | J37: =IF(OR(Inputs!K9>=3,Inputs!D9="Unemployed",Inputs!P9<0),"POLICY DECLINE","Pass") -> Pass | K37: =IF(J37="POLICY DECLINE","Decline",IF(H37>=Assumptions!$B$17,"Approve",IF(H37>=Assumptions!$B$18,"Review","Decline"))) -> Approve
A38: =Inputs!A10 -> SA-2025-007 | B38: =IF(Inputs!J10>=750,25,IF(Inputs!J10>=700,20,IF(Inputs!J10>=650,13,IF(Inputs!J10>=580,5,0)))) -> 0 | C38: =IF(Inputs!O10<0.3,20,IF(Inputs!O10<0.4,14,IF(Inputs!O10<0.5,7,IF(Inputs!O10<0.6,2,0)))) -> 20 | D38: =IF(Inputs!P10>12000,20,IF(Inputs!P10>=6000,14,IF(Inputs!P10>=2000,7,IF(Inputs!P10>=0,2,0)))) -> 0 | E38: =IF(Inputs!D10="Permanently Employed",15,IF(Inputs!D10="Self-Employed",10,IF(Inputs!D10="Fixed-Term Contract",5,0))) -> 0 | F38: =IF(Inputs!K10=0,10,IF(Inputs!K10=1,6,IF(Inputs!K10=2,2,0))) -> 0 | G38: =IF(Inputs!L10>=10,10,IF(Inputs!L10>=5,7,IF(Inputs!L10>=2,4,1))) -> 1 | H38: =SUM(B38:G38) -> 21 | I38: =IF(H38>=Assumptions!$B$16,"Low Risk",IF(H38>=Assumptions!$B$17,"Medium Risk","High Risk")) -> High Risk | J38: =IF(OR(Inputs!K10>=3,Inputs!D10="Unemployed",Inputs!P10<0),"POLICY DECLINE","Pass") -> POLICY DECLINE | K38: =IF(J38="POLICY DECLINE","Decline",IF(H38>=Assumptions!$B$17,"Approve",IF(H38>=Assumptions!$B$18,"Review","Decline"))) -> Decline
A39: =Inputs!A11 -> SA-2025-008 | B39: =IF(Inputs!J11>=750,25,IF(Inputs!J11>=700,20,IF(Inputs!J11>=650,13,IF(Inputs!J11>=580,5,0)))) -> 20 | C39: =IF(Inputs!O11<0.3,20,IF(Inputs!O11<0.4,14,IF(Inputs!O11<0.5,7,IF(Inputs!O11<0.6,2,0)))) -> 7 | D39: =IF(Inputs!P11>12000,20,IF(Inputs!P11>=6000,14,IF(Inputs!P11>=2000,7,IF(Inputs!P11>=0,2,0)))) -> 14 | E39: =IF(Inputs!D11="Permanently Employed",15,IF(Inputs!D11="Self-Employed",10,IF(Inputs!D11="Fixed-Term Contract",5,0))) -> 10 | F39: =IF(Inputs!K11=0,10,IF(Inputs!K11=1,6,IF(Inputs!K11=2,2,0))) -> 10 | G39: =IF(Inputs!L11>=10,10,IF(Inputs!L11>=5,7,IF(Inputs!L11>=2,4,1))) -> 10 | H39: =SUM(B39:G39) -> 71 | I39: =IF(H39>=Assumptions!$B$16,"Low Risk",IF(H39>=Assumptions!$B$17,"Medium Risk","High Risk")) -> Low Risk | J39: =IF(OR(Inputs!K11>=3,Inputs!D11="Unemployed",Inputs!P11<0),"POLICY DECLINE","Pass") -> Pass | K39: =IF(J39="POLICY DECLINE","Decline",IF(H39>=Assumptions!$B$17,"Approve",IF(H39>=Assumptions!$B$18,"Review","Decline"))) -> Approve
A40: =Inputs!A12 -> SA-2025-009 | B40: =IF(Inputs!J12>=750,25,IF(Inputs!J12>=700,20,IF(Inputs!J12>=650,13,IF(Inputs!J12>=580,5,0)))) -> 13 | C40: =IF(Inputs!O12<0.3,20,IF(Inputs!O12<0.4,14,IF(Inputs!O12<0.5,7,IF(Inputs!O12<0.6,2,0)))) -> 20 | D40: =IF(Inputs!P12>12000,20,IF(Inputs!P12>=6000,14,IF(Inputs!P12>=2000,7,IF(Inputs!P12>=0,2,0)))) -> 20 | E40: =IF(Inputs!D12="Permanently Employed",15,IF(Inputs!D12="Self-Employed",10,IF(Inputs!D12="Fixed-Term Contract",5,0))) -> 15 | F40: =IF(Inputs!K12=0,10,IF(Inputs!K12=1,6,IF(Inputs!K12=2,2,0))) -> 10 | G40: =IF(Inputs!L12>=10,10,IF(Inputs!L12>=5,7,IF(Inputs!L12>=2,4,1))) -> 7 | H40: =SUM(B40:G40) -> 85 | I40: =IF(H40>=Assumptions!$B$16,"Low Risk",IF(H40>=Assumptions!$B$17,"Medium Risk","High Risk")) -> Low Risk | J40: =IF(OR(Inputs!K12>=3,Inputs!D12="Unemployed",Inputs!P12<0),"POLICY DECLINE","Pass") -> Pass | K40: =IF(J40="POLICY DECLINE","Decline",IF(H40>=Assumptions!$B$17,"Approve",IF(H40>=Assumptions!$B$18,"Review","Decline"))) -> Approve
A41: =Inputs!A13 -> SA-2025-010 | B41: =IF(Inputs!J13>=750,25,IF(Inputs!J13>=700,20,IF(Inputs!J13>=650,13,IF(Inputs!J13>=580,5,0)))) -> 5 | C41: =IF(Inputs!O13<0.3,20,IF(Inputs!O13<0.4,14,IF(Inputs!O13<0.5,7,IF(Inputs!O13<0.6,2,0)))) -> 14 | D41: =IF(Inputs!P13>12000,20,IF(Inputs!P13>=6000,14,IF(Inputs!P13>=2000,7,IF(Inputs!P13>=0,2,0)))) -> 7 | E41: =IF(Inputs!D13="Permanently Employed",15,IF(Inputs!D13="Self-Employed",10,IF(Inputs!D13="Fixed-Term Contract",5,0))) -> 5 | F41: =IF(Inputs!K13=0,10,IF(Inputs!K13=1,6,IF(Inputs!K13=2,2,0))) -> 6 | G41: =IF(Inputs!L13>=10,10,IF(Inputs!L13>=5,7,IF(Inputs!L13>=2,4,1))) -> 4 | H41: =SUM(B41:G41) -> 41 | I41: =IF(H41>=Assumptions!$B$16,"Low Risk",IF(H41>=Assumptions!$B$17,"Medium Risk","High Risk")) -> High Risk | J41: =IF(OR(Inputs!K13>=3,Inputs!D13="Unemployed",Inputs!P13<0),"POLICY DECLINE","Pass") -> Pass | K41: =IF(J41="POLICY DECLINE","Decline",IF(H41>=Assumptions!$B$17,"Approve",IF(H41>=Assumptions!$B$18,"Review","Decline"))) -> Decline
A42: =Inputs!A14 -> SA-2025-011 | B42: =IF(Inputs!J14>=750,25,IF(Inputs!J14>=700,20,IF(Inputs!J14>=650,13,IF(Inputs!J14>=580,5,0)))) -> 25 | C42: =IF(Inputs!O14<0.3,20,IF(Inputs!O14<0.4,14,IF(Inputs!O14<0.5,7,IF(Inputs!O14<0.6,2,0)))) -> 20 | D42: =IF(Inputs!P14>12000,20,IF(Inputs!P14>=6000,14,IF(Inputs!P14>=2000,7,IF(Inputs!P14>=0,2,0)))) -> 20 | E42: =IF(Inputs!D14="Permanently Employed",15,IF(Inputs!D14="Self-Employed",10,IF(Inputs!D14="Fixed-Term Contract",5,0))) -> 15 | F42: =IF(Inputs!K14=0,10,IF(Inputs!K14=1,6,IF(Inputs!K14=2,2,0))) -> 10 | G42: =IF(Inputs!L14>=10,10,IF(Inputs!L14>=5,7,IF(Inputs!L14>=2,4,1))) -> 10 | H42: =SUM(B42:G42) -> 100 | I42: =IF(H42>=Assumptions!$B$16,"Low Risk",IF(H42>=Assumptions!$B$17,"Medium Risk","High Risk")) -> Low Risk | J42: =IF(OR(Inputs!K14>=3,Inputs!D14="Unemployed",Inputs!P14<0),"POLICY DECLINE","Pass") -> Pass | K42: =IF(J42="POLICY DECLINE","Decline",IF(H42>=Assumptions!$B$17,"Approve",IF(H42>=Assumptions!$B$18,"Review","Decline"))) -> Approve
A43: =Inputs!A15 -> SA-2025-012 | B43: =IF(Inputs!J15>=750,25,IF(Inputs!J15>=700,20,IF(Inputs!J15>=650,13,IF(Inputs!J15>=580,5,0)))) -> 5 | C43: =IF(Inputs!O15<0.3,20,IF(Inputs!O15<0.4,14,IF(Inputs!O15<0.5,7,IF(Inputs!O15<0.6,2,0)))) -> 20 | D43: =IF(Inputs!P15>12000,20,IF(Inputs!P15>=6000,14,IF(Inputs!P15>=2000,7,IF(Inputs!P15>=0,2,0)))) -> 20 | E43: =IF(Inputs!D15="Permanently Employed",15,IF(Inputs!D15="Self-Employed",10,IF(Inputs!D15="Fixed-Term Contract",5,0))) -> 15 | F43: =IF(Inputs!K15=0,10,IF(Inputs!K15=1,6,IF(Inputs!K15=2,2,0))) -> 2 | G43: =IF(Inputs!L15>=10,10,IF(Inputs!L15>=5,7,IF(Inputs!L15>=2,4,1))) -> 7 | H43: =SUM(B43:G43) -> 69 | I43: =IF(H43>=Assumptions!$B$16,"Low Risk",IF(H43>=Assumptions!$B$17,"Medium Risk","High Risk")) -> Low Risk | J43: =IF(OR(Inputs!K15>=3,Inputs!D15="Unemployed",Inputs!P15<0),"POLICY DECLINE","Pass") -> Pass | K43: =IF(J43="POLICY DECLINE","Decline",IF(H43>=Assumptions!$B$17,"Approve",IF(H43>=Assumptions!$B$18,"Review","Decline"))) -> Approve
... A61: =Inputs!A33 -> SA-2025-030 | B61: =IF(Inputs!J33>=750,25,IF(Inputs!J33>=700,20,IF(Inputs!J33>=650,13,IF(Inputs!J33>=580,5,0)))) -> 0 | C61: =IF(Inputs!O33<0.3,20,IF(Inputs!O33<0.4,14,IF(Inputs!O33<0.5,7,IF(Inputs!O33<0.6,2,0)))) -> 20 | D61: =IF(Inputs!P33>12000,20,IF(Inputs!P33>=6000,14,IF(Inputs!P33>=2000,7,IF(Inputs!P33>=0,2,0)))) -> 7 | E61: =IF(Inputs!D33="Permanently Employed",15,IF(Inputs!D33="Self-Employed",10,IF(Inputs!D33="Fixed-Term Contract",5,0))) -> 5 | F61: =IF(Inputs!K33=0,10,IF(Inputs!K33=1,6,IF(Inputs!K33=2,2,0))) -> 2 | G61: =IF(Inputs!L33>=10,10,IF(Inputs!L33>=5,7,IF(Inputs!L33>=2,4,1))) -> 1 | H61: =SUM(B61:G61) -> 35 | I61: =IF(H61>=Assumptions!$B$16,"Low Risk",IF(H61>=Assumptions!$B$17,"Medium Risk","High Risk")) -> High Risk | J61: =IF(OR(Inputs!K33>=3,Inputs!D33="Unemployed",Inputs!P33<0),"POLICY DECLINE","Pass") -> Pass | K61: =IF(J61="POLICY DECLINE","Decline",IF(H61>=Assumptions!$B$17,"Approve",IF(H61>=Assumptions!$B$18,"Review","Decline"))) -> Decline
A63: DECISION THRESHOLDS (from Assumptions sheet): Score ≥ 68 = APPROVE (Low Risk) | Score 42–67 = REVIEW (Medium Risk) | Score < 42 = DECLINE (High Risk) | Policy overrides apply regardless of score

Sheet Decision Output
A1: SA RETAIL CREDIT SCORECARD | DECISION OUTPUT & REASON FLAGS | FY2025
A2: DECISION SUMMARY | E2: RISK DRIVER FLAGS (⚠ = flag triggered)
A3: Applicant ID | B3: Total Score (/100) | C3: Risk Band | D3: Final Decision | E3: ⚠ Low Credit Score (<580) | F3: ⚠ High DTI (≥50%) | G3: ⚠ Thin Surplus (<R2k) | H3: ⚠ Missed Payments (2+) | I3: ⚠ Short Tenure (<2 yrs) | J3: ⚠ Policy Override
A4: ='Scorecard Logic'!A32 -> SA-2025-001 | B4: ='Scorecard Logic'!H32 -> 92 | C4: ='Scorecard Logic'!I32 -> Low Risk | D4: ='Scorecard Logic'!K32 -> Approve | E4: =IF(Inputs!J4<580,"⚠ Low CS","") | F4: =IF(Inputs!O4>=0.5,"⚠ DTI {}"&TEXT(Inputs!O4,"0%"),"") | G4: =IF(Inputs!P4<2000,"⚠ Surplus R"&TEXT(Inputs!P4,"#,##0"),"") | H4: =IF(Inputs!K4>=2,"⚠ "&Inputs!K4&" missed","") | I4: =IF(Inputs!L4<2,"⚠ "&Inputs!L4&" yr(s)","") | J4: =IF('Scorecard Logic'!J32="POLICY DECLINE","⚠ Policy Override","")
A5: ='Scorecard Logic'!A33 -> SA-2025-002 | B5: ='Scorecard Logic'!H33 -> 70 | C5: ='Scorecard Logic'!I33 -> Low Risk | D5: ='Scorecard Logic'!K33 -> Approve | E5: =IF(Inputs!J5<580,"⚠ Low CS","") | F5: =IF(Inputs!O5>=0.5,"⚠ DTI {}"&TEXT(Inputs!O5,"0%"),"") | G5: =IF(Inputs!P5<2000,"⚠ Surplus R"&TEXT(Inputs!P5,"#,##0"),"") | H5: =IF(Inputs!K5>=2,"⚠ "&Inputs!K5&" missed","") | I5: =IF(Inputs!L5<2,"⚠ "&Inputs!L5&" yr(s)","") | J5: =IF('Scorecard Logic'!J33="POLICY DECLINE","⚠ Policy Override","")
A6: ='Scorecard Logic'!A34 -> SA-2025-003 | B6: ='Scorecard Logic'!H34 -> 83 | C6: ='Scorecard Logic'!I34 -> Low Risk | D6: ='Scorecard Logic'!K34 -> Approve | E6: =IF(Inputs!J6<580,"⚠ Low CS","") | F6: =IF(Inputs!O6>=0.5,"⚠ DTI {}"&TEXT(Inputs!O6,"0%"),"") | G6: =IF(Inputs!P6<2000,"⚠ Surplus R"&TEXT(Inputs!P6,"#,##0"),"") | H6: =IF(Inputs!K6>=2,"⚠ "&Inputs!K6&" missed","") | I6: =IF(Inputs!L6<2,"⚠ "&Inputs!L6&" yr(s)","") | J6: =IF('Scorecard Logic'!J34="POLICY DECLINE","⚠ Policy Override","")
A7: ='Scorecard Logic'!A35 -> SA-2025-004 | B7: ='Scorecard Logic'!H35 -> 47 | C7: ='Scorecard Logic'!I35 -> Medium Risk | D7: ='Scorecard Logic'!K35 -> Approve | E7: =IF(Inputs!J7<580,"⚠ Low CS","") | F7: =IF(Inputs!O7>=0.5,"⚠ DTI {}"&TEXT(Inputs!O7,"0%"),"") | G7: =IF(Inputs!P7<2000,"⚠ Surplus R"&TEXT(Inputs!P7,"#,##0"),"") | H7: =IF(Inputs!K7>=2,"⚠ "&Inputs!K7&" missed","") -> ⚠ 2 missed | I7: =IF(Inputs!L7<2,"⚠ "&Inputs!L7&" yr(s)","") -> ⚠ 1 yr(s) | J7: =IF('Scorecard Logic'!J35="POLICY DECLINE","⚠ Policy Override","")
A8: ='Scorecard Logic'!A36 -> SA-2025-005 | B8: ='Scorecard Logic'!H36 -> 64 | C8: ='Scorecard Logic'!I36 -> Medium Risk | D8: ='Scorecard Logic'!K36 -> Approve | E8: =IF(Inputs!J8<580,"⚠ Low CS","") | F8: =IF(Inputs!O8>=0.5,"⚠ DTI {}"&TEXT(Inputs!O8,"0%"),"") -> ⚠ DTI {}57% | G8: =IF(Inputs!P8<2000,"⚠ Surplus R"&TEXT(Inputs!P8,"#,##0"),"") | H8: =IF(Inputs!K8>=2,"⚠ "&Inputs!K8&" missed","") | I8: =IF(Inputs!L8<2,"⚠ "&Inputs!L8&" yr(s)","") | J8: =IF('Scorecard Logic'!J36="POLICY DECLINE","⚠ Policy Override","")
A9: ='Scorecard Logic'!A37 -> SA-2025-006 | B9: ='Scorecard Logic'!H37 -> 81 | C9: ='Scorecard Logic'!I37 -> Low Risk | D9: ='Scorecard Logic'!K37 -> Approve | E9: =IF(Inputs!J9<580,"⚠ Low CS","") | F9: =IF(Inputs!O9>=0.5,"⚠ DTI {}"&TEXT(Inputs!O9,"0%"),"") | G9: =IF(Inputs!P9<2000,"⚠ Surplus R"&TEXT(Inputs!P9,"#,##0"),"") | H9: =IF(Inputs!K9>=2,"⚠ "&Inputs!K9&" missed","") | I9: =IF(Inputs!L9<2,"⚠ "&Inputs!L9&" yr(s)","") | J9: =IF('Scorecard Logic'!J37="POLICY DECLINE","⚠ Policy Override","")
A10: ='Scorecard Logic'!A38 -> SA-2025-007 | B10: ='Scorecard Logic'!H38 -> 21 | C10: ='Scorecard Logic'!I38 -> High Risk | D10: ='Scorecard Logic'!K38 -> Decline | E10: =IF(Inputs!J10<580,"⚠ Low CS","") -> ⚠ Low CS | F10: =IF(Inputs!O10>=0.5,"⚠ DTI {}"&TEXT(Inputs!O10,"0%"),"") | G10: =IF(Inputs!P10<2000,"⚠ Surplus R"&TEXT(Inputs!P10,"#,##0"),"") -> ⚠ Surplus R-6841,056 | H10: =IF(Inputs!K10>=2,"⚠ "&Inputs!K10&" missed","") -> ⚠ 4 missed | I10: =IF(Inputs!L10<2,"⚠ "&Inputs!L10&" yr(s)","") -> ⚠ 0 yr(s) | J10: =IF('Scorecard Logic'!J38="POLICY DECLINE","⚠ Policy Override","") -> ⚠ Policy Override
A11: ='Scorecard Logic'!A39 -> SA-2025-008 | B11: ='Scorecard Logic'!H39 -> 71 | C11: ='Scorecard Logic'!I39 -> Low Risk | D11: ='Scorecard Logic'!K39 -> Approve | E11: =IF(Inputs!J11<580,"⚠ Low CS","") | F11: =IF(Inputs!O11>=0.5,"⚠ DTI {}"&TEXT(Inputs!O11,"0%"),"") | G11: =IF(Inputs!P11<2000,"⚠ Surplus R"&TEXT(Inputs!P11,"#,##0"),"") | H11: =IF(Inputs!K11>=2,"⚠ "&Inputs!K11&" missed","") | I11: =IF(Inputs!L11<2,"⚠ "&Inputs!L11&" yr(s)","") | J11: =IF('Scorecard Logic'!J39="POLICY DECLINE","⚠ Policy Override","")
A12: ='Scorecard Logic'!A40 -> SA-2025-009 | B12: ='Scorecard Logic'!H40 -> 85 | C12: ='Scorecard Logic'!I40 -> Low Risk | D12: ='Scorecard Logic'!K40 -> Approve | E12: =IF(Inputs!J12<580,"⚠ Low CS","") | F12: =IF(Inputs!O12>=0.5,"⚠ DTI {}"&TEXT(Inputs!O12,"0%"),"") | G12: =IF(Inputs!P12<2000,"⚠ Surplus R"&TEXT(Inputs!P12,"#,##0"),"") | H12: =IF(Inputs!K12>=2,"⚠ "&Inputs!K12&" missed","") | I12: =IF(Inputs!L12<2,"⚠ "&Inputs!L12&" yr(s)","") | J12: =IF('Scorecard Logic'!J40="POLICY DECLINE","⚠ Policy Override","")
A13: ='Scorecard Logic'!A41 -> SA-2025-010 | B13: ='Scorecard Logic'!H41 -> 41 | C13: ='Scorecard Logic'!I41 -> High Risk | D13: ='Scorecard Logic'!K41 -> Decline | E13: =IF(Inputs!J13<580,"⚠ Low CS","") | F13: =IF(Inputs!O13>=0.5,"⚠ DTI {}"&TEXT(Inputs!O13,"0%"),"") | G13: =IF(Inputs!P13<2000,"⚠ Surplus R"&TEXT(Inputs!P13,"#,##0"),"") | H13: =IF(Inputs!K13>=2,"⚠ "&Inputs!K13&" missed","") | I13: =IF(Inputs!L13<2,"⚠ "&Inputs!L13&" yr(s)","") | J13: =IF('Scorecard Logic'!J41="POLICY DECLINE","⚠ Policy Override","")
A14: ='Scorecard Logic'!A42 -> SA-2025-011 | B14: ='Scorecard Logic'!H42 -> 100 | C14: ='Scorecard Logic'!I42 -> Low Risk | D14: ='Scorecard Logic'!K42 -> Approve | E14: =IF(Inputs!J14<580,"⚠ Low CS","") | F14: =IF(Inputs!O14>=0.5,"⚠ DTI {}"&TEXT(Inputs!O14,"0%"),"") | G14: =IF(Inputs!P14<2000,"⚠ Surplus R"&TEXT(Inputs!P14,"#,##0"),"") | H14: =IF(Inputs!K14>=2,"⚠ "&Inputs!K14&" missed","") | I14: =IF(Inputs!L14<2,"⚠ "&Inputs!L14&" yr(s)","") | J14: =IF('Scorecard Logic'!J42="POLICY DECLINE","⚠ Policy Override","")
A15: ='Scorecard Logic'!A43 -> SA-2025-012 | B15: ='Scorecard Logic'!H43 -> 69 | C15: ='Scorecard Logic'!I43 -> Low Risk | D15: ='Scorecard Logic'!K43 -> Approve | E15: =IF(Inputs!J15<580,"⚠ Low CS","") | F15: =IF(Inputs!O15>=0.5,"⚠ DTI {}"&TEXT(Inputs!O15,"0%"),"") | G15: =IF(Inputs!P15<2000,"⚠ Surplus R"&TEXT(Inputs!P15,"#,##0"),"") | H15: =IF(Inputs!K15>=2,"⚠ "&Inputs!K15&" missed","") -> ⚠ 2 missed | I15: =IF(Inputs!L15<2,"⚠ "&Inputs!L15&" yr(s)","") | J15: =IF('Scorecard Logic'!J43="POLICY DECLINE","⚠ Policy Override","")
... A33: ='Scorecard Logic'!A61 -> SA-2025-030 | B33: ='Scorecard Logic'!H61 -> 35 | C33: ='Scorecard Logic'!I61 -> High Risk | D33: ='Scorecard Logic'!K61 -> Decline | E33: =IF(Inputs!J33<580,"⚠ Low CS","") -> ⚠ Low CS | F33: =IF(Inputs!O33>=0.5,"⚠ DTI {}"&TEXT(Inputs!O33,"0%"),"") | G33: =IF(Inputs!P33<2000,"⚠ Surplus R"&TEXT(Inputs!P33,"#,##0"),"") | H33: =IF(Inputs!K33>=2,"⚠ "&Inputs!K33&" missed","") -> ⚠ 2 missed | I33: =IF(Inputs!L33<2,"⚠ "&Inputs!L33&" yr(s)","") -> ⚠ 0 yr(s) | J33: =IF('Scorecard Logic'!J61="POLICY DECLINE","⚠ Policy Override","")

Sheet Dashboard Data
A1: SA RETAIL CREDIT SCORECARD | PORTFOLIO ANALYTICS DASHBOARD | FY2025
A3: A. PORTFOLIO DECISION SUMMARY | F3: C. RISK BAND DISTRIBUTION
A4: Metric | B4: Value | C4: % of Portfolio | F4: Risk Band | G4: Count | H4: % of Portfolio
A5: Total Applications | B5: =COUNTA('Decision Output'!A4:A33) -> 30 | F5: Low Risk | G5: =COUNTIF('Decision Output'!C4:C33,"Low Risk") -> 18 | H5: =IFERROR(G5/B5,0) -> 0.6
A6: Approved | B6: =COUNTIF('Decision Output'!D4:D33,"Approve") -> 23 | C6: =IFERROR(B6/B5,0) -> 0.76666667 | F6: Medium Risk | G6: =COUNTIF('Decision Output'!C4:C33,"Medium Risk") -> 5 | H6: =IFERROR(G6/B5,0) -> 0.16666667
A7: Under Review | B7: =COUNTIF('Decision Output'!D4:D33,"Review") -> 0 | C7: =IFERROR(B7/B5,0) -> 0 | F7: High Risk | G7: =COUNTIF('Decision Output'!C4:C33,"High Risk") -> 7 | H7: =IFERROR(G7/B5,0) -> 0.23333333
A8: Declined | B8: =COUNTIF('Decision Output'!D4:D33,"Decline") -> 7 | C8: =IFERROR(B8/B5,0) -> 0.23333333
A9: Policy Override Declines | B9: =COUNTIF('Scorecard Logic'!J32:J61,"POLICY DECLINE") -> 4 | C9: =IFERROR(B9/B5,0) -> 0.13333333 | F9: D. EMPLOYMENT STATUS vs DECISION
F10: Employment Type | G10: Approved | H10: Declined
F11: Permanently Employed | G11: =COUNTIFS(Inputs!D4:D33,"Permanently Employed",'Decision Output'!D4:D33,"Approve") -> 16 | H11: =COUNTIFS(Inputs!D4:D33,"Permanently Employed",'Decision Output'!D4:D33,"Decline") -> 0
A12: B. AVERAGE PORTFOLIO RISK METRICS | F12: Self-Employed | G12: =COUNTIFS(Inputs!D4:D33,"Self-Employed",'Decision Output'!D4:D33,"Approve") -> 6 | H12: =COUNTIFS(Inputs!D4:D33,"Self-Employed",'Decision Output'!D4:D33,"Decline") -> 0
A13: Metric | B13: Portfolio Avg | C13: Approved Avg | F13: Fixed-Term Contract | G13: =COUNTIFS(Inputs!D4:D33,"Fixed-Term Contract",'Decision Output'!D4:D33,"Approve") -> 1 | H13: =COUNTIFS(Inputs!D4:D33,"Fixed-Term Contract",'Decision Output'!D4:D33,"Decline") -> 5
A14: Average Total Score (/100) | B14: =IFERROR(AVERAGE('Decision Output'!B4:B33),0) -> 68.833333 | C14: =IFERROR(AVERAGEIF('Decision Output'!D4:D33,"Approve",'Decision Output'!B4:B33),0) -> 80.173913 | F14: Unemployed | G14: =COUNTIFS(Inputs!D4:D33,"Unemployed",'Decision Output'!D4:D33,"Approve") -> 0 | H14: =COUNTIFS(Inputs!D4:D33,"Unemployed",'Decision Output'!D4:D33,"Decline") -> 2
A15: Average Credit Score | B15: =IFERROR(AVERAGE(Inputs!J4:J33),0) -> 666.03333 | C15: =IFERROR(AVERAGEIF('Decision Output'!D4:D33,"Approve",Inputs!J4:J33),0) -> 696.13043
A16: Average DTI | B16: =IFERROR(AVERAGE(Inputs!O4:O33),0) -> 0.23201694 | C16: =IFERROR(AVERAGEIF('Decision Output'!D4:D33,"Approve",Inputs!O4:O33),0) -> 0.25085953 | F16: E. APPLICATIONS BY PROVINCE
A17: Average Affordability Surplus (R) | B17: =IFERROR(AVERAGE(Inputs!P4:P33),0) -> 14023.518 | C17: =IFERROR(AVERAGEIF('Decision Output'!D4:D33,"Approve",Inputs!P4:P33),0) -> 17849.382 | F17: Province | G17: Count | H17: Approval Rate
F18: Gauteng | G18: =COUNTIF(Inputs!C4:C33,"Gauteng") -> 13 | H18: =IFERROR(COUNTIFS(Inputs!C4:C33,"Gauteng",'Decision Output'!D4:D33,"Approve")/G18,0) -> 0.92307692
A19: F. CHART-READY DATA TABLES | F19: Western Cape | G19: =COUNTIF(Inputs!C4:C33,"Western Cape") -> 8 | H19: =IFERROR(COUNTIFS(Inputs!C4:C33,"Western Cape",'Decision Output'!D4:D33,"Approve")/G19,0) -> 1
A20: Decision Distribution (for Pie / Donut Chart) | F20: KwaZulu-Natal | G20: =COUNTIF(Inputs!C4:C33,"KwaZulu-Natal") -> 4 | H20: =IFERROR(COUNTIFS(Inputs!C4:C33,"KwaZulu-Natal",'Decision Output'!D4:D33,"Approve")/G20,0) -> 0.5
A21: Category | B21: Count | C21: Rate | F21: Eastern Cape | G21: =COUNTIF(Inputs!C4:C33,"Eastern Cape") -> 2 | H21: =IFERROR(COUNTIFS(Inputs!C4:C33,"Eastern Cape",'Decision Output'!D4:D33,"Approve")/G21,0) -> 0
A22: Approve | B22: =COUNTIF('Decision Output'!D4:D33,"Approve") -> 23 | C22: =IFERROR(B22/B5,0) -> 0.76666667 | F22: Limpopo | G22: =COUNTIF(Inputs!C4:C33,"Limpopo") -> 1 | H22: =IFERROR(COUNTIFS(Inputs!C4:C33,"Limpopo",'Decision Output'!D4:D33,"Approve")/G22,0) -> 0
A23: Review | B23: =COUNTIF('Decision Output'!D4:D33,"Review") -> 0 | C23: =IFERROR(B23/B5,0) -> 0 | F23: North West | G23: =COUNTIF(Inputs!C4:C33,"North West") -> 1 | H23: =IFERROR(COUNTIFS(Inputs!C4:C33,"North West",'Decision Output'!D4:D33,"Approve")/G23,0) -> 1
A24: Decline | B24: =COUNTIF('Decision Output'!D4:D33,"Decline") -> 7 | C24: =IFERROR(B24/B5,0) -> 0.23333333 | F24: Mpumalanga | G24: =COUNTIF(Inputs!C4:C33,"Mpumalanga") -> 1 | H24: =IFERROR(COUNTIFS(Inputs!C4:C33,"Mpumalanga",'Decision Output'!D4:D33,"Approve")/G24,0) -> 0
A26: Score Distribution (for Histogram / Bar Chart)
A27: Score Bracket | B27: Count
A28: 0 – 29 | B28: =COUNTIFS('Decision Output'!B4:B33,">=0",'Decision Output'!B4:B33,"<30") -> 2
A29: 30 – 49 | B29: =COUNTIFS('Decision Output'!B4:B33,">=30",'Decision Output'!B4:B33,"<50") -> 6
A30: 50 – 67 | B30: =COUNTIFS('Decision Output'!B4:B33,">=50",'Decision Output'!B4:B33,"<68") -> 4
A31: 68 – 84 | B31: =COUNTIFS('Decision Output'!B4:B33,">=68",'Decision Output'!B4:B33,"<85") -> 7
A32: 85 – 100 | B32: =COUNTIFS('Decision Output'!B4:B33,">=85",'Decision Output'!B4:B33,"<101") -> 11

Sheet README
A1: SA RETAIL CREDIT SCORECARD MODEL | TECHNICAL DOCUMENTATION | SIPHESIHLE GWEBU
A3: PROJECT OVERVIEW
A4: This workbook implements a retail credit scorecard designed to reflect the decisioning logic used by South African banks under the National Credit Act (NCA). It evaluates 30 synthetic loan applicants across six weighted risk factors and produces a scored lending decision — Approve, Review, or Decline — with reason flags and portfolio analytics. All assumptions are centralised on the Assumptions sheet for audit-trail transparency.
A5: REGULATORY CONTEXT
A6: South African consumer credit is governed by the National Credit Act 34 of 2005 (NCA) and overseen by the National Credit Regulator (NCR). Key principles embedded in this model:
A7: • Section 81 (Reckless Credit): Lenders must conduct affordability assessments before extending credit.
A8: • Section 86 (Over-indebtedness): A consumer is over-indebted if they cannot meet all obligations — DTI thresholds reflect this.
A9: • NCR Affordability Guidelines: Maximum DTI of approximately 35–40% for unsecured lending is standard bank policy.
A10: • Credit Bureau Data: Credit scores sourced from TransUnion or Experian (SA) range 330–850. This model uses that range.
A11: WORKBOOK STRUCTURE
A12: Assumptions Centralised rate, threshold, and policy variables (change here — model updates everywhere)
A13: Inputs 30 SA applicants with income, expenses, debt, bureau score, and employment profile
... A52: Built by: Siphesihle Gwebu | Junior Management Accountant
